Metadata-Version: 2.1
Name: computer_info
Version: 1.0.1
Summary: This package is used to view system and hardware information.
Author: Xingyuan55
Author-email: dus0963@outlook.com
Classifier: Programming Language :: Python :: 3.8
Classifier: License :: OSI Approved :: Mozilla Public License 2.0 (MPL 2.0)
License-File: LICENSE
